{
  "records": [
    {
      "Name": "Word Bell",
      "Location": "Dellas,Texas",
      "orders": 1,
      "image" :"/images/User.jpg"
    },
      {
          "Name": "Word Bell",
          "Location": "Dellas,Texas",
          "orders": 1,
          "image" :"/images/User.jpg"
      },
      {
          "Name": "Robin Cleark",
          "Location": "Los Angels,California",
          "orders": 2,
          "image" :"/images/User.jpg"
      },
      {
          "Name": "Albert Einstien",
          "Location": "Settle,Washington",
          "orders": 3,
          "image" :"/images/User.jpg"
      },
      {
          "Name": "Albert Raja",
          "Location": "Anehim,California",
          "orders": 4,
          "image" :"/images/User.jpg"
      },
      {
          "Name": "Albert Kumar",
          "Location": "Phoenix,Arezona",
          "orders": 5,
          "image" :"/images/User.jpg"
      },
      {
          "Name": "Candy Jamison",
          "Location": "Chandier,Arizona",
          "orders": 6,
          "image" :"/images/User.jpg"
      },
      {
          "Name": "Candy Crush",
          "Location": "Dallas,Texas",
          "orders": 7,
          "image" :"/images/User.jpg"
      },
      {
          "Name": "Candy Meroon",
          "Location": "Newyork",
          "orders": 8,
          "image" :"/images/User.jpg"
      },
      {
          "Name": "Candy sharon",
          "Location": "Dellas,Texas",
          "orders": 9,
          "image" :"/images/User.jpg"
      },
      {
          "Name": "Rajkumar",
          "Location": "Dellas,Texas",
          "orders": 10,
          "image" :"/images/User.jpg"
      },
      {
          "Name": "Rajkumar",
          "Location": "Dellas,Texas",
          "orders": 111,
          "image" :"/images/User.jpg"
      },
      {
          "Name": "Rajkumar",
          "Location": "Dellas,Texas",
          "orders": 12,
          "image" :"/images/User.jpg"
      },
      {
          "Name": "Rajkumar",
          "Location": "Dellas,Texas",
          "orders": 13,
          "image" :"/images/User.jpg"
      },
      {
          "Name": "Albert Raja",
          "Location": "Anehim,California",
          "orders": 4,
          "image" :"/images/User.jpg"
      },
      {
          "Name": "Albert Kumar",
          "Location": "Phoenix,Arezona",
          "orders": 5,
          "image" :"/images/User.jpg"
      },
      {
          "Name": "Candy Jamison",
          "Location": "Chandier,Arizona",
          "orders": 6,
          "image" :"/images/User.jpg"
      },
      {
          "Name": "Candy Crush",
          "Location": "Dallas,Texas",
          "orders": 7,
          "image" :"/images/User.jpg"
      },
      {
          "Name": "Candy Meroon",
          "Location": "Newyork",
          "orders": 8,
          "image" :"/images/User.jpg"
      },
      {
          "Name": "Candy sharon",
          "Location": "Dellas,Texas",
          "orders": 9,
          "image" :"/images/User.jpg"
      },
      {
          "Name": "Rajkumar",
          "Location": "Dellas,Texas",
          "orders": 10,
          "image" :"/images/User.jpg"
      },
      {
          "Name": "Rajkumar",
          "Location": "Dellas,Texas",
          "orders": 111,
          "image" :"/images/User.jpg"
      },
      {
          "Name": "Rajkumar",
          "Location": "Dellas,Texas",
          "orders": 12,
          "image" :"/images/User.jpg"
      },
      {
          "Name": "Rajkumar",
          "Location": "Dellas,Texas",
          "orders": 13,
          "image" :"/images/User.jpg"
      },
      {
          "Name": "Rajkumar",
          "Location": "Dellas,Texas",
          "orders": 14,
          "image" :"/images/User.jpg"
      },
    {
        "Name": "Robin Cleark",
        "Location": "Los Angels,California",
        "orders": 2,
        "image" :"/images/User.jpg"
    },
    {
        "Name": "Albert Einstien",
        "Location": "Settle,Washington",
        "orders": 3,
        "image" :"/images/User.jpg"
    },
    {
        "Name": "Albert Raja",
        "Location": "Anehim,California",
        "orders": 4,
        "image" :"/images/User.jpg"
    },
    {
        "Name": "Albert Kumar",
        "Location": "Phoenix,Arezona",
        "orders": 5,
        "image" :"/images/User.jpg"
    },
    {
        "Name": "Candy Jamison",
        "Location": "Chandier,Arizona",
        "orders": 6,
        "image" :"/images/User.jpg"
    },
    {
        "Name": "Candy Crush",
        "Location": "Dallas,Texas",
        "orders": 7,
        "image" :"/images/User.jpg"
    },
    {
        "Name": "Candy Meroon",
        "Location": "Newyork",
        "orders": 8,
        "image" :"/images/User.jpg"
    },
    {
        "Name": "Candy sharon",
        "Location": "Dellas,Texas",
        "orders": 9,
        "image" :"/images/User.jpg"
    },
    {
        "Name": "Rajkumar",
        "Location": "Dellas,Texas",
        "orders": 10,
        "image" :"/images/User.jpg"
    },
    {
        "Name": "Rajkumar",
        "Location": "Dellas,Texas",
        "orders": 111,
        "image" :"/images/User.jpg"
    },
    {
        "Name": "Rajkumar",
        "Location": "Dellas,Texas",
        "orders": 12,
        "image" :"/images/User.jpg"
    },
    {
        "Name": "Rajkumar",
        "Location": "Dellas,Texas",
        "orders": 13,
        "image" :"/images/User.jpg"
    },
    {
        "Name": "Rajkumar",
        "Location": "Dellas,Texas",
        "orders": 14,
        "image" :"/images/User.jpg"
    },
    {
        "Name": "Rajkumar",
        "Location": "Dellas,Texas",
        "orders": 15,
        "image" :"/images/User.jpg"
    }
  ]
}